crete/__init__.py
crete/__main__.py
crete/agent.py
crete/core.py
crete/error.py
crete/global_state.py
crete/registration.py
crete/types.py
crete/util.py
crete/cli/__init__.py
crete/cli/cli_utils.py
crete/cli/concfile.py
crete/cli/list.py
crete/cli/main.py
crete/cli/module.py
crete/file/__init__.py
crete/file/concrete.py
crete/file/crete_config.py
crete/file/profile.py
crete-0.2.0.dist-info/LICENSE
crete-0.2.0.dist-info/METADATA
crete-0.2.0.dist-info/WHEEL
crete-0.2.0.dist-info/top_level.txt
crete-0.2.0.dist-info/RECORD
