Metadata-Version: 2.1
Name: crete
Version: 0.2.0
Summary: An RL agent training assistant
Author-email: Blair Cross <blair@bxsys.dev>
Classifier: Programming Language :: Python :: 3
Classifier: License :: OSI Approved :: MIT License
Classifier: Operating System :: OS Independent
Requires-Python: >=3.7
License-File: LICENSE
Requires-Dist: numpy
Requires-Dist: Gymnasium
Requires-Dist: typer[all]
Requires-Dist: PyYAML (==6.0)
Requires-Dist: pygame
Requires-Dist: matplotlib
